genome_ninja/_cli.py
genome_ninja/__init__.py
genome_ninja/_fast_reader.cpython-39-darwin.so
genome_ninja/tools/fast_fna_size.py
genome_ninja/tools/__init__.py
genome_ninja/core/io.py
genome_ninja/core/utils.py
genome_ninja/plugins/__init__.py
genome_ninja/_cpp/CMakeLists.txt
genome_ninja/_cpp/fast_reader.cpp
genome_ninja/_cpp/pybind_fast_reader.cpp
genome_ninja/_cpp/fast_reader.hpp
genome_ninja/data/quotes.txt
genome_ninja-0.0.1.dist-info/RECORD
genome_ninja-0.0.1.dist-info/WHEEL
genome_ninja-0.0.1.dist-info/entry_points.txt
genome_ninja-0.0.1.dist-info/METADATA
genome_ninja-0.0.1.dist-info/licenses/LICENSE
